monies/__init__.py
monies/__itinerary/later.S.HTML
monies/_licenses/gpl-3.0-standalone.html
monies/_ops/_clique/__init__.py
monies/_ops/_clique/group/__init__.py
monies/_status/DB/records.json
monies/_status/monitors/status_1.py
monies/_status/status.proc.py
monies/adventures/stack.S.HTML
monies/license.S.HTML
monies/mixer.MD
monies/mixer.S.HTML
monies-0.0.2.dist-info/METADATA
monies-0.0.2.dist-info/WHEEL
monies-0.0.2.dist-info/entry_points.txt
monies-0.0.2.dist-info/RECORD
