Metadata-Version: 2.1
Name: monies
Version: 0.0.2
Summary: MongoDB ops
License: licensed
Requires-Python: >=3.10,<4.0
Classifier: License :: Other/Proprietary License
Classifier: Programming Language :: Python :: 3
Classifier: Programming Language :: Python :: 3.10
Classifier: Programming Language :: Python :: 3.11
Classifier: Programming Language :: Python :: 3.12
Requires-Dist: biotech (>=1.1.10,<2.0.0)
Requires-Dist: click (>=8.1.7,<9.0.0)
Requires-Dist: somatic (>=3.0.3,<4.0.0)
